setup.py
sstvProxy.py
YAPSSTV/sstvProxy.py
YAPSSTV.egg-info/PKG-INFO
YAPSSTV.egg-info/SOURCES.txt
YAPSSTV.egg-info/dependency_links.txt
YAPSSTV.egg-info/requires.txt
YAPSSTV.egg-info/top_level.txt
yapsstv/sstvProxy.py
yapsstv.egg-info/PKG-INFO
yapsstv.egg-info/SOURCES.txt
yapsstv.egg-info/dependency_links.txt
yapsstv.egg-info/requires.txt
yapsstv.egg-info/top_level.txt