Metadata-Version: 1.2
Name: YAPSSTV
Version: 1.1
Summary: Yet Another Proxy
Home-page: UNKNOWN
Author: UNKNOWN
Author-email: UNKNOWN
License: UNKNOWN
Platform: UNKNOWN
Requires-Python: >=3.5
